README
setup.cfg
setup.py
comboloader/__init__.py
comboloader/app.py
comboloader.egg-info/PKG-INFO
comboloader.egg-info/SOURCES.txt
comboloader.egg-info/dependency_links.txt
comboloader.egg-info/entry_points.txt
comboloader.egg-info/not-zip-safe
comboloader.egg-info/requires.txt
comboloader.egg-info/top_level.txt
comboloader/utils/__init__.py
comboloader/utils/request.py