Metadata-Version: 1.0
Name: comboloader
Version: 0.1dev
Summary: WSGI App for combining JS and CSS files and returning a single request.
Home-page: http://www.surveymonkey.com
Author: Chris George
Author-email: chris.george@surveymonkey.com
License: GPL
Keywords: combo,comboloader,combine,javascript,cascading style sheets,css,js
Platform: UNKNOWN
